datastructures/__init__.py
datastructuresLionelHandEricM/__init__.py
datastructuresLionelHandEricM-0.4.dist-info/METADATA
datastructuresLionelHandEricM-0.4.dist-info/WHEEL
datastructuresLionelHandEricM-0.4.dist-info/top_level.txt
datastructuresLionelHandEricM-0.4.dist-info/RECORD
