Metadata-Version: 2.1
Name: datastructuresLionelHandEricM
Version: 0.4
Summary: Variety of datastructures implemented in Python
Home-page: UNKNOWN
Author: Lionel Hasan & Eric Mei
Author-email: lionel.hasan@ucalgary.ca
License: UNKNOWN
Platform: UNKNOWN
